paytm_verifier/__init__.py
paytm_verifier/verifier.py
paytm_verifier-1.0.3.dist-info/licenses/LICENSE
paytm_verifier-1.0.3.dist-info/METADATA
paytm_verifier-1.0.3.dist-info/WHEEL
paytm_verifier-1.0.3.dist-info/top_level.txt
paytm_verifier-1.0.3.dist-info/RECORD
