Metadata-Version: 2.4
Name: paytm-verifier
Version: 1.0.3
Summary: Verify Paytm merchant payments using MID and Order ID.
Home-page: https://github.com/Uday-x-ai/paytm-verifier
Author: UdayScripts
Author-email: support@udayscripts.in
Project-URL: Telegram, https://t.me/UdayScripts
Classifier: Programming Language :: Python :: 3
Classifier: License :: OSI Approved :: MIT License
Classifier: Operating System :: OS Independent
Requires-Python: >=3.7
License-File: LICENSE
Requires-Dist: requests
Dynamic: author
Dynamic: author-email
Dynamic: classifier
Dynamic: description
Dynamic: description-content-type
Dynamic: home-page
Dynamic: license-file
Dynamic: project-url
Dynamic: requires-dist
Dynamic: requires-python
Dynamic: summary
